{
  "0": {
    "js": [
      "http://localhost:3001/static/js/0.chunk.js"
    ],
    "map": [
      "http://localhost:3001/static/js/0.chunk.js.map"
    ],
    "chunks": [
      0
    ]
  },
  "1": {
    "js": [
      "http://localhost:3001/static/js/1.chunk.js"
    ],
    "map": [
      "http://localhost:3001/static/js/1.chunk.js.map"
    ],
    "chunks": [
      1
    ]
  },
  "2": {
    "js": [
      "http://localhost:3001/static/js/2.chunk.js"
    ],
    "map": [
      "http://localhost:3001/static/js/2.chunk.js.map"
    ],
    "chunks": [
      2
    ]
  },
  "3": {
    "js": [
      "http://localhost:3001/static/js/3.chunk.js"
    ],
    "map": [
      "http://localhost:3001/static/js/3.chunk.js.map"
    ],
    "chunks": [
      3
    ]
  },
  "4": {
    "js": [
      "http://localhost:3001/static/js/4.chunk.js"
    ],
    "map": [
      "http://localhost:3001/static/js/4.chunk.js.map"
    ],
    "chunks": [
      4
    ]
  },
  "5": {
    "js": [
      "http://localhost:3001/static/js/5.chunk.js"
    ],
    "map": [
      "http://localhost:3001/static/js/5.chunk.js.map"
    ],
    "chunks": [
      5
    ]
  },
  "6": {
    "js": [
      "http://localhost:3001/static/js/6.chunk.js"
    ],
    "map": [
      "http://localhost:3001/static/js/6.chunk.js.map"
    ],
    "chunks": [
      6
    ]
  },
  "7": {
    "js": [
      "http://localhost:3001/static/js/7.chunk.js"
    ],
    "map": [
      "http://localhost:3001/static/js/7.chunk.js.map"
    ],
    "chunks": [
      7
    ]
  },
  "8": {
    "js": [
      "http://localhost:3001/static/js/8.chunk.js"
    ],
    "map": [
      "http://localhost:3001/static/js/8.chunk.js.map"
    ],
    "chunks": [
      8
    ]
  },
  "9": {
    "js": [
      "http://localhost:3001/static/js/9.chunk.js"
    ],
    "map": [
      "http://localhost:3001/static/js/9.chunk.js.map"
    ],
    "chunks": [
      9
    ]
  },
  "10": {
    "js": [
      "http://localhost:3001/static/js/10.chunk.js"
    ],
    "map": [
      "http://localhost:3001/static/js/10.chunk.js.map"
    ],
    "chunks": [
      10
    ]
  },
  "11": {
    "js": [
      "http://localhost:3001/static/js/11.chunk.js"
    ],
    "map": [
      "http://localhost:3001/static/js/11.chunk.js.map"
    ],
    "chunks": [
      11
    ]
  },
  "client": {
    "js": [
      "http://localhost:3001/static/js/runtime~client.js",
      "http://localhost:3001/static/js/client.chunk.js"
    ],
    "map": [
      "http://localhost:3001/static/js/runtime~client.js.map",
      "http://localhost:3001/static/js/client.chunk.js.map"
    ],
    "chunks": [
      "runtime~client",
      "client"
    ]
  },
  "diff": {
    "js": [
      "http://localhost:3001/static/js/diff.chunk.js"
    ],
    "map": [
      "http://localhost:3001/static/js/diff.chunk.js.map"
    ],
    "chunks": [
      "diff"
    ]
  },
  "draft-js": {
    "js": [
      "http://localhost:3001/static/js/draft-js.chunk.js"
    ],
    "map": [
      "http://localhost:3001/static/js/draft-js.chunk.js.map"
    ],
    "chunks": [
      "draft-js"
    ]
  },
  "draft-js-block-breakout-plugin": {
    "js": [
      "http://localhost:3001/static/js/draft-js-block-breakout-plugin.chunk.js"
    ],
    "map": [
      "http://localhost:3001/static/js/draft-js-block-breakout-plugin.chunk.js.map"
    ],
    "chunks": [
      "draft-js-block-breakout-plugin"
    ]
  },
  "draft-js-buttons-lib-utils-createBlockStyleButton": {
    "js": [
      "http://localhost:3001/static/js/draft-js-buttons-lib-utils-createBlockStyleButton.chunk.js"
    ],
    "map": [
      "http://localhost:3001/static/js/draft-js-buttons-lib-utils-createBlockStyleButton.chunk.js.map"
    ],
    "chunks": [
      "draft-js-buttons-lib-utils-createBlockStyleButton"
    ]
  },
  "draft-js-buttons-lib-utils-createInlineStyleButton": {
    "js": [
      "http://localhost:3001/static/js/draft-js-buttons-lib-utils-createInlineStyleButton.chunk.js"
    ],
    "map": [
      "http://localhost:3001/static/js/draft-js-buttons-lib-utils-createInlineStyleButton.chunk.js.map"
    ],
    "chunks": [
      "draft-js-buttons-lib-utils-createInlineStyleButton"
    ]
  },
  "draft-js-import-html": {
    "js": [
      "http://localhost:3001/static/js/draft-js-import-html.chunk.js"
    ],
    "map": [
      "http://localhost:3001/static/js/draft-js-import-html.chunk.js.map"
    ],
    "chunks": [
      "draft-js-import-html"
    ]
  },
  "draft-js-inline-toolbar-plugin": {
    "js": [
      "http://localhost:3001/static/js/draft-js-inline-toolbar-plugin.chunk.js"
    ],
    "map": [
      "http://localhost:3001/static/js/draft-js-inline-toolbar-plugin.chunk.js.map"
    ],
    "chunks": [
      "draft-js-inline-toolbar-plugin"
    ]
  },
  "draft-js-lib-isSoftNewlineEvent": {
    "js": [
      "http://localhost:3001/static/js/draft-js-lib-isSoftNewlineEvent.chunk.js"
    ],
    "map": [
      "http://localhost:3001/static/js/draft-js-lib-isSoftNewlineEvent.chunk.js.map"
    ],
    "chunks": [
      "draft-js-lib-isSoftNewlineEvent"
    ]
  },
  "draft-js-plugins-editor": {
    "js": [
      "http://localhost:3001/static/js/draft-js-plugins-editor.chunk.js"
    ],
    "map": [
      "http://localhost:3001/static/js/draft-js-plugins-editor.chunk.js.map"
    ],
    "chunks": [
      "draft-js-plugins-editor"
    ]
  },
  "draft-js-plugins-utils": {
    "js": [
      "http://localhost:3001/static/js/draft-js-plugins-utils.chunk.js"
    ],
    "map": [
      "http://localhost:3001/static/js/draft-js-plugins-utils.chunk.js.map"
    ],
    "chunks": [
      "draft-js-plugins-utils"
    ]
  },
  "draftjs-filters": {
    "js": [
      "http://localhost:3001/static/js/draftjs-filters.chunk.js"
    ],
    "map": [
      "http://localhost:3001/static/js/draftjs-filters.chunk.js.map"
    ],
    "chunks": [
      "draftjs-filters"
    ]
  },
  "immutable": {
    "js": [
      "http://localhost:3001/static/js/immutable.chunk.js"
    ],
    "map": [
      "http://localhost:3001/static/js/immutable.chunk.js.map"
    ],
    "chunks": [
      "immutable"
    ]
  },
  "plone-volto-components-manage-Widgets-RecurrenceWidget-RecurrenceWidget": {
    "js": [
      "http://localhost:3001/static/js/plone-volto-components-manage-Widgets-RecurrenceWidget-RecurrenceWidget.chunk.js"
    ],
    "map": [
      "http://localhost:3001/static/js/plone-volto-components-manage-Widgets-RecurrenceWidget-RecurrenceWidget.chunk.js.map"
    ],
    "chunks": [
      "plone-volto-components-manage-Widgets-RecurrenceWidget-RecurrenceWidget"
    ]
  },
  "plone-volto-components-theme-View-EventView": {
    "js": [
      "http://localhost:3001/static/js/plone-volto-components-theme-View-EventView.chunk.js"
    ],
    "map": [
      "http://localhost:3001/static/js/plone-volto-components-theme-View-EventView.chunk.js.map"
    ],
    "chunks": [
      "plone-volto-components-theme-View-EventView"
    ]
  },
  "prettier-parser-html": {
    "js": [
      "http://localhost:3001/static/js/prettier-parser-html.chunk.js"
    ],
    "map": [
      "http://localhost:3001/static/js/prettier-parser-html.chunk.js.map"
    ],
    "chunks": [
      "prettier-parser-html"
    ]
  },
  "prettier-standalone": {
    "js": [
      "http://localhost:3001/static/js/prettier-standalone.chunk.js"
    ],
    "map": [
      "http://localhost:3001/static/js/prettier-standalone.chunk.js.map"
    ],
    "chunks": [
      "prettier-standalone"
    ]
  },
  "prismjs-components-prism-core": {
    "js": [
      "http://localhost:3001/static/js/prismjs-components-prism-core.chunk.js"
    ],
    "map": [
      "http://localhost:3001/static/js/prismjs-components-prism-core.chunk.js.map"
    ],
    "chunks": [
      "prismjs-components-prism-core"
    ]
  },
  "rc-time-picker": {
    "js": [
      "http://localhost:3001/static/js/rc-time-picker.chunk.js"
    ],
    "map": [
      "http://localhost:3001/static/js/rc-time-picker.chunk.js.map"
    ],
    "chunks": [
      "rc-time-picker"
    ]
  },
  "react-dates": {
    "js": [
      "http://localhost:3001/static/js/react-dates.chunk.js"
    ],
    "map": [
      "http://localhost:3001/static/js/react-dates.chunk.js.map"
    ],
    "chunks": [
      "react-dates"
    ]
  },
  "react-dnd": {
    "js": [
      "http://localhost:3001/static/js/react-dnd.chunk.js"
    ],
    "map": [
      "http://localhost:3001/static/js/react-dnd.chunk.js.map"
    ],
    "chunks": [
      "react-dnd"
    ]
  },
  "react-dnd-html5-backend": {
    "js": [
      "http://localhost:3001/static/js/react-dnd-html5-backend.chunk.js"
    ],
    "map": [
      "http://localhost:3001/static/js/react-dnd-html5-backend.chunk.js.map"
    ],
    "chunks": [
      "react-dnd-html5-backend"
    ]
  },
  "react-image-gallery": {
    "js": [
      "http://localhost:3001/static/js/react-image-gallery.chunk.js"
    ],
    "map": [
      "http://localhost:3001/static/js/react-image-gallery.chunk.js.map"
    ],
    "chunks": [
      "react-image-gallery"
    ]
  },
  "react-select": {
    "js": [
      "http://localhost:3001/static/js/react-select.chunk.js"
    ],
    "map": [
      "http://localhost:3001/static/js/react-select.chunk.js.map"
    ],
    "chunks": [
      "react-select"
    ]
  },
  "react-select-async": {
    "js": [
      "http://localhost:3001/static/js/react-select-async.chunk.js"
    ],
    "map": [
      "http://localhost:3001/static/js/react-select-async.chunk.js.map"
    ],
    "chunks": [
      "react-select-async"
    ]
  },
  "react-select-async-creatable": {
    "js": [
      "http://localhost:3001/static/js/react-select-async-creatable.chunk.js"
    ],
    "map": [
      "http://localhost:3001/static/js/react-select-async-creatable.chunk.js.map"
    ],
    "chunks": [
      "react-select-async-creatable"
    ]
  },
  "react-select-async-paginate": {
    "js": [
      "http://localhost:3001/static/js/react-select-async-paginate.chunk.js"
    ],
    "map": [
      "http://localhost:3001/static/js/react-select-async-paginate.chunk.js.map"
    ],
    "chunks": [
      "react-select-async-paginate"
    ]
  },
  "react-select-creatable": {
    "js": [
      "http://localhost:3001/static/js/react-select-creatable.chunk.js"
    ],
    "map": [
      "http://localhost:3001/static/js/react-select-creatable.chunk.js.map"
    ],
    "chunks": [
      "react-select-creatable"
    ]
  },
  "react-simple-code-editor": {
    "js": [
      "http://localhost:3001/static/js/react-simple-code-editor.chunk.js"
    ],
    "map": [
      "http://localhost:3001/static/js/react-simple-code-editor.chunk.js.map"
    ],
    "chunks": [
      "react-simple-code-editor"
    ]
  },
  "react-sortable-hoc": {
    "js": [
      "http://localhost:3001/static/js/react-sortable-hoc.chunk.js"
    ],
    "map": [
      "http://localhost:3001/static/js/react-sortable-hoc.chunk.js.map"
    ],
    "chunks": [
      "react-sortable-hoc"
    ]
  },
  "react-virtualized": {
    "js": [
      "http://localhost:3001/static/js/react-virtualized.chunk.js"
    ],
    "map": [
      "http://localhost:3001/static/js/react-virtualized.chunk.js.map"
    ],
    "chunks": [
      "react-virtualized"
    ]
  },
  "rrule": {
    "js": [
      "http://localhost:3001/static/js/rrule.chunk.js"
    ],
    "map": [
      "http://localhost:3001/static/js/rrule.chunk.js.map"
    ],
    "chunks": [
      "rrule"
    ]
  },
  "noentry": {
    "svg": [
      "http://localhost:3001/static/media/Logo.16e25cdf.svg",
      "http://localhost:3001/static/media/block-image.8a4a14d5.svg",
      "http://localhost:3001/static/media/block-maps.731e84f6.svg",
      "http://localhost:3001/static/media/block-video.832fa3ff.svg",
      "http://localhost:3001/static/media/default-image.9451b251.svg",
      "http://localhost:3001/static/media/grid-1.f89d5f8b.svg",
      "http://localhost:3001/static/media/grid-2.4068e674.svg",
      "http://localhost:3001/static/media/grid-3.19cf9f8d.svg",
      "http://localhost:3001/static/media/grid-4.2b07a173.svg",
      "http://localhost:3001/static/media/grid-5.b5b500b1.svg",
      "http://localhost:3001/static/media/grid-6.3a790adb.svg",
      "http://localhost:3001/static/media/grid-more.63c498e3.svg",
      "http://localhost:3001/static/media/icons.022583c4.svg",
      "http://localhost:3001/static/media/slick.f97e3bbf.svg"
    ],
    "woff2": [
      "http://localhost:3001/static/media/Poppins-Bold-devanagari.7def222d.woff2",
      "http://localhost:3001/static/media/Poppins-Bold-latin.25b0e113.woff2",
      "http://localhost:3001/static/media/Poppins-Bold-latinext.96b6d546.woff2",
      "http://localhost:3001/static/media/Poppins-BoldItalic-devanagari.17352fe0.woff2",
      "http://localhost:3001/static/media/Poppins-BoldItalic-latin.858549c2.woff2",
      "http://localhost:3001/static/media/Poppins-BoldItalic-latinext.34ad495c.woff2",
      "http://localhost:3001/static/media/Poppins-Light-devanagari.dc820d9f.woff2",
      "http://localhost:3001/static/media/Poppins-Light-latin.8d91ec1c.woff2",
      "http://localhost:3001/static/media/Poppins-Light-latinext.6731e1ba.woff2",
      "http://localhost:3001/static/media/Poppins-Regular-devanagari.790d0c8d.woff2",
      "http://localhost:3001/static/media/Poppins-Regular-latin.9212f6f9.woff2",
      "http://localhost:3001/static/media/Poppins-Regular-latinext.0ed299a4.woff2",
      "http://localhost:3001/static/media/Poppins-RegularItalic-devanagari.ba7c820d.woff2",
      "http://localhost:3001/static/media/Poppins-RegularItalic-latin.a242ba0d.woff2",
      "http://localhost:3001/static/media/Poppins-RegularItalic-latinext.efd6a6a1.woff2",
      "http://localhost:3001/static/media/Poppins-Semibold-devanagari.79e6e81d.woff2",
      "http://localhost:3001/static/media/Poppins-Semibold-latin.a09f2fcc.woff2",
      "http://localhost:3001/static/media/Poppins-Semibold-latinext.a6ff41d1.woff2"
    ],
    "png": [
      "http://localhost:3001/static/media/flags.9c74e172.png"
    ],
    "ttf": [
      "http://localhost:3001/static/media/icons.06400145.ttf",
      "http://localhost:3001/static/media/slick.d41f55a7.ttf"
    ],
    "eot": [
      "http://localhost:3001/static/media/icons.dbc1ef8b.eot",
      "http://localhost:3001/static/media/slick.ced611da.eot"
    ],
    "woff": [
      "http://localhost:3001/static/media/icons.df45b7de.woff",
      "http://localhost:3001/static/media/slick.b7c9e1e4.woff"
    ]
  }
}